challtools/__init__.py
challtools/challenge.schema.json
challtools/codes.yml
challtools/constants.py
challtools/context.py
challtools/entry.py
challtools/exceptions.py
challtools/plugin.py
challtools/types.py
challtools/utils.py
challtools/validator.py
challtools/builtins/__init__.py
challtools/builtins/allchalls.py
challtools/builtins/build.py
challtools/builtins/compose.py
challtools/builtins/ensureid.py
challtools/builtins/init.py
challtools/builtins/push.py
challtools/builtins/solve.py
challtools/builtins/spoilerfree.py
challtools/builtins/start.py
challtools/builtins/validate.py
challtools/templates/default/DESCRIPTION
challtools/templates/default/challenge.yml
challtools/templates/flask/DESCRIPTION
challtools/templates/flask/challenge.yml
challtools/templates/flask/container/Dockerfile
challtools/templates/flask/container/nginx.conf
challtools/templates/flask/container/server.py
challtools/templates/php/DESCRIPTION
challtools/templates/php/challenge.yml
challtools/templates/php/container/Dockerfile
challtools/templates/php/container/index.php
challtools/templates/ssh/DESCRIPTION
challtools/templates/ssh/challenge.yml
challtools/templates/ssh/container/Dockerfile
challtools/templates/ssh/container/service
challtools/templates/ssh/container/sshd_config
challtools/templates/tcp_nsjail/DESCRIPTION
challtools/templates/tcp_nsjail/challenge.yml
challtools/templates/tcp_nsjail/container/Dockerfile
challtools/templates/tcp_nsjail/container/service
challtools/templates/tls_nsjail/DESCRIPTION
challtools/templates/tls_nsjail/challenge.yml
challtools/templates/tls_nsjail/container/Dockerfile
challtools/templates/tls_nsjail/container/haproxy.cfg
challtools/templates/tls_nsjail/container/service
challtools-0.5.0.dist-info/LICENSE
challtools-0.5.0.dist-info/METADATA
challtools-0.5.0.dist-info/WHEEL
challtools-0.5.0.dist-info/entry_points.txt
challtools-0.5.0.dist-info/top_level.txt
challtools-0.5.0.dist-info/RECORD
