Metadata-Version: 2.2
Name: challtools
Version: 0.5.0
Summary: A tool for managing CTF challenges and challenge repositories using the OpenChallSpec
Author-email: Mateusz Drwal <challtools@mateuszdrwal.com>
Project-URL: repository, https://github.com/mateuszdrwal/challtools
Classifier: Programming Language :: Python :: 3
Classifier: License :: OSI Approved :: MIT License
Classifier: Operating System :: OS Independent
Requires-Python: >=3.9
License-File: LICENSE
Requires-Dist: PyYAML
Requires-Dist: jsonschema>=3.0.0
Requires-Dist: docker!=3.1.2,!=5.0.0,>=2.3.0
Requires-Dist: requests>=2.0.0
Requires-Dist: pypiwin32; platform_system == "Windows"
Requires-Dist: argcomplete>=2.0.0
Provides-Extra: dev
Requires-Dist: pytest; extra == "dev"
Requires-Dist: pytest-cov; extra == "dev"
Requires-Dist: pwntools; extra == "dev"
